{
  "accountAssociation": {
    "header": "eyJmaWQiOjU4MDczOCwidHlwZSI6ImN1c3RvZHkiLCJrZXkiOiIweDEwOUM5ZTgwMTNFY2U4ODZENGY4QUUyNjkyNTRkZTkzMEFFZmNkNDQifQ",
    "payload": "eyJkb21haW4iOiJiYXNlLXJhZmZsZS1wbHVtLnZlcmNlbC5hcHAifQ",
    "signature": "5RcmFwRWB1bFOZIhZS4tQmcGpGZ5EjovSB/EGP98cVN/Ni65oeV18Moo63LsRxNNGddEOckCzwaqax6RxtEPDBs="
  },
  "miniapp": {
    "version": "1",
    "name": "BaseRaffle",
    "homeUrl": "https://base-raffle-plum.vercel.app",
    "imageUrl": "https://base-raffle-plum.vercel.app/cover-1200x630.png",
    "iconUrl": "https://base-raffle-plum.vercel.app/icon-1024.png",
    "splashImageUrl": "https://base-raffle-plum.vercel.app/splash.png",
    "splashBackgroundColor": "#0a0a0f",
    "subtitle": "Fair Raffles on Base",
    "description": "Create and participate in provably fair raffles on Base. Powered by Chainlink VRF for true randomness.",
    "screenshotUrls": [
      "https://base-raffle-plum.vercel.app/screenshots/screenshot-1.png",
      "https://base-raffle-plum.vercel.app/screenshots/screenshot-2.png",
      "https://base-raffle-plum.vercel.app/screenshots/screenshot-3.png"
    ],
    "primaryCategory": "games",
    "tags": ["raffle", "lottery", "base", "chainlink", "vrf"],
    "heroImageUrl": "https://base-raffle-plum.vercel.app/cover-1200x630.png",
    "tagline": "Provably Fair Raffles",
    "ogTitle": "BaseRaffle - Fair Raffles",
    "ogDescription": "Create and participate in provably fair raffles on Base. Powered by Chainlink VRF.",
    "ogImageUrl": "https://base-raffle-plum.vercel.app/cover-1200x630.png",
    "noindex": false
  }
}
